jobs_detector/__init__.py
jobs_detector/exceptions.py
jobs_detector/main.py
jobs_detector/settings.py
rmotr_b6_c1_g2_jobs_detector-0.0.2.dist-info/DESCRIPTION.rst
rmotr_b6_c1_g2_jobs_detector-0.0.2.dist-info/METADATA
rmotr_b6_c1_g2_jobs_detector-0.0.2.dist-info/RECORD
rmotr_b6_c1_g2_jobs_detector-0.0.2.dist-info/WHEEL
rmotr_b6_c1_g2_jobs_detector-0.0.2.dist-info/entry_points.txt
rmotr_b6_c1_g2_jobs_detector-0.0.2.dist-info/metadata.json
rmotr_b6_c1_g2_jobs_detector-0.0.2.dist-info/top_level.txt
