Metadata-Version: 2.0
Name: rmotr-b6-c1-g2-jobs-detector
Version: 0.0.2
Summary: rmotr.com Group Project | Jobs Detector
Home-page: https://github.com/duddles/pyp-w3-gw-jobs-detector
Author: rmotr.com
Author-email: questions@rmotr.com
License: CC BY-SA 4.0 License
Platform: UNKNOWN
Requires-Dist: bs4
Requires-Dist: click
Requires-Dist: coverage
Requires-Dist: pytest
Requires-Dist: pytest-cov
Requires-Dist: responses
Requires-Dist: tox
